overcode/__init__.py
overcode/cli.py
overcode/config.py
overcode/daemon_claude_skill.md
overcode/daemon_logging.py
overcode/daemon_utils.py
overcode/data_export.py
overcode/dependency_check.py
overcode/exceptions.py
overcode/history_reader.py
overcode/implementations.py
overcode/interfaces.py
overcode/launcher.py
overcode/logging_config.py
overcode/mocks.py
overcode/monitor_daemon.py
overcode/monitor_daemon_state.py
overcode/pid_utils.py
overcode/presence_logger.py
overcode/protocols.py
overcode/session_manager.py
overcode/settings.py
overcode/standing_instructions.py
overcode/status_constants.py
overcode/status_detector.py
overcode/status_history.py
overcode/status_patterns.py
overcode/summarizer_client.py
overcode/summarizer_component.py
overcode/supervisor_daemon.py
overcode/supervisor_layout.sh
overcode/tmux_manager.py
overcode/tui.py
overcode/tui_helpers.py
overcode/web_api.py
overcode/web_chartjs.py
overcode/web_server.py
overcode/web_server_runner.py
overcode/web_templates.py
overcode-0.1.3.dist-info/licenses/LICENSE
overcode-0.1.3.dist-info/METADATA
overcode-0.1.3.dist-info/WHEEL
overcode-0.1.3.dist-info/entry_points.txt
overcode-0.1.3.dist-info/top_level.txt
overcode-0.1.3.dist-info/RECORD
