Metadata-Version: 2.4
Name: overcode
Version: 0.1.3
Summary: A supervisor for managing multiple Claude Code instances in tmux
Author: Mike Bond
Project-URL: Homepage, https://github.com/mkb23/overcode
Project-URL: Repository, https://github.com/mkb23/overcode
Project-URL: Issues, https://github.com/mkb23/overcode/issues
Classifier: Development Status :: 4 - Beta
Classifier: Environment :: Console
Classifier: Intended Audience :: Developers
Classifier: License :: OSI Approved :: MIT License
Classifier: Operating System :: MacOS
Classifier: Operating System :: POSIX :: Linux
Classifier: Programming Language :: Python :: 3
Classifier: Programming Language :: Python :: 3.12
Classifier: Programming Language :: Python :: 3.13
Classifier: Topic :: Software Development :: Quality Assurance
Requires-Python: >=3.12
License-File: LICENSE
Requires-Dist: textual>=0.40.0
Requires-Dist: rich>=13.0.0
Requires-Dist: typer>=0.9.0
Requires-Dist: pyyaml>=6.0
Requires-Dist: libtmux>=0.37.0
Provides-Extra: dev
Requires-Dist: pytest>=7.0.0; extra == "dev"
Requires-Dist: pytest-asyncio>=0.21.0; extra == "dev"
Requires-Dist: pytest-cov>=4.0.0; extra == "dev"
Requires-Dist: pytest-timeout>=2.1.0; extra == "dev"
Requires-Dist: black>=23.0.0; extra == "dev"
Requires-Dist: mypy>=1.0.0; extra == "dev"
Provides-Extra: presence
Requires-Dist: pyobjc-framework-Quartz>=10.0; extra == "presence"
Requires-Dist: pyobjc-framework-ApplicationServices>=10.0; extra == "presence"
Provides-Extra: export
Requires-Dist: pyarrow>=14.0.0; extra == "export"
Dynamic: license-file
